scratch3_analyzer/__init__.py
scratch3_analyzer/__main__.py
scratch3_analyzer/analyzer.py
scratch3_analyzer/cli.py
scratch3_analyzer/core.py
scratch3_analyzer/exporter.py
scratch3_analyzer/extractor.py
scratch3_analyzer/gui.py
scratch3_analyzer-1.1.1.dist-info/licenses/LICENSE
scratch3_analyzer-1.1.1.dist-info/METADATA
scratch3_analyzer-1.1.1.dist-info/WHEEL
scratch3_analyzer-1.1.1.dist-info/entry_points.txt
scratch3_analyzer-1.1.1.dist-info/top_level.txt
scratch3_analyzer-1.1.1.dist-info/RECORD
