Metadata-Version: 2.4
Name: scratch3_analyzer
Version: 1.1.1
Summary: A comprehensive Python library to extract, analyze, and export detailed statistics from Scratch 3.0 (.sb3) project files.
Author-email: jzm <939370014@qq.com>
License: AGPL
Project-URL: Homepage, https://github.com/jzm3/scratch3_analyzer
Keywords: scratch,sb3,analysis,education,coding,visual-programming
Classifier: Development Status :: 4 - Beta
Classifier: Intended Audience :: Education
Classifier: Intended Audience :: Developers
Classifier: Topic :: Education
Classifier: Topic :: Software Development :: Libraries :: Python Modules
Classifier: Programming Language :: Python :: 3
Classifier: Programming Language :: Python :: 3.7
Classifier: Programming Language :: Python :: 3.8
Classifier: Programming Language :: Python :: 3.9
Classifier: Programming Language :: Python :: 3.10
Classifier: Programming Language :: Python :: 3.11
Classifier: Operating System :: OS Independent
Requires-Python: >=3.7
License-File: LICENSE
Requires-Dist: pandas>=1.3.0
Requires-Dist: openpyxl>=3.0.0
Dynamic: license-file
